{"type":"PR","pr":{"number":325,"head":"a4c27743be8552ea4add2babe3da09cd31d24d69"},"user":"multiforma","status":"draft","branch":"cms/atenção-para-nossos-horários-nos-feriados-de-páscoa-e-tiradentes","collection":"blog","title":"Atenção para nossos horários nos feriados de Páscoa e Tiradentes.","description":"No Description!","objects":{"entry":{"path":"src/admin/content/blog/atenção-para-nossos-horários-nos-feriados-de-páscoa-e-tiradentes.md","sha":"2c8d44d9b0e37ef84adba52f8f1a1fb760b02641"},"files":[{"path":"/src/admin/content/media/cale.jpg","sha":"450d0067946e8f98894e10ee2d9b18559585af81"}]},"timeStamp":"2025-04-16T17:28:51.979Z"}