{"type":"PR","pr":{"number":306,"head":"df2db852056fe4641a951ba4c80ec616ef084c7f"},"user":"multiforma","status":"draft","branch":"cms/correção-do-fgts-deve-ter-reposição-da-inflação","collection":"blog","title":"Correção do FGTS deve ter reposição da inflação","description":"No Description!","objects":{"entry":{"path":"src/admin/content/blog/correção-do-fgts-deve-ter-reposição-da-inflação.md","sha":"0a53bdba720f91a27494aa686eddb7145474c37e"},"files":[{"path":"/src/admin/content/media/ssl.jpg","sha":"2ccf872912197e18c88924f354b861b80467b7f7"}]},"timeStamp":"2024-07-17T12:46:46.585Z"}