{"type":"PR","pr":{"number":237,"head":"7b60b40fd92b2f86da0667442a0fc8a2cede3b86"},"user":"Guilherme-SLPG","status":"pending_publish","branch":"cms/o-slpg-não-terá-expediente-no-carnaval","collection":"blog","title":"O SLPG não terá expediente no carnaval","description":"No Description!","objects":{"entry":{"path":"src/admin/content/blog/o-slpg-não-terá-expediente-no-carnaval.md","sha":"569321baf16ab7c6ded701b3e135a30f3368da23"},"files":[{"path":"/src/admin/content/media/aaa.jpeg","sha":"10c79a00f1e3a4f44676c84ed42d1ac629640de5"}]},"timeStamp":"2023-02-15T13:42:54.378Z"}